pyxdaq/__init__.py
pyxdaq/board.py
pyxdaq/constants.py
pyxdaq/datablock.py
pyxdaq/gen2.py
pyxdaq/impedance.py
pyxdaq/intan_headstage.py
pyxdaq/register.py
pyxdaq/rhd_driver.py
pyxdaq/rhs_driver.py
pyxdaq/stim.py
pyxdaq/utils.py
pyxdaq/xdaq.py
pyxdaq/resources/__init__.py
pyxdaq/resources/config/isa_rhd.json
pyxdaq/resources/config/isa_rhs.json
pyxdaq/resources/config/reg_rhd.json
pyxdaq/resources/config/reg_rhs.json
pyxdaq/tools/self_diagnosis.py
pyxdaq-0.3.1.dist-info/licenses/LICENSE
pyxdaq-0.3.1.dist-info/METADATA
pyxdaq-0.3.1.dist-info/WHEEL
pyxdaq-0.3.1.dist-info/entry_points.txt
pyxdaq-0.3.1.dist-info/top_level.txt
pyxdaq-0.3.1.dist-info/RECORD
