Metadata-Version: 2.4
Name: pyxdaq
Version: 0.3.1
License-Expression: MIT
Project-URL: Homepage, https://github.com/kontex-neuro/pyxdaq
Requires-Python: >=3.11
License-File: LICENSE
Requires-Dist: colorlog
Requires-Dist: dataclass_wizard
Requires-Dist: pylibxdaq==0.4.*
Requires-Dist: numpy
Requires-Dist: rich
Requires-Dist: tqdm
Requires-Dist: matplotlib
Requires-Dist: tzdata
Dynamic: license-file
